github_actions_cdk/cdktf_provider_aws/__init__.py
github_actions_cdk/cdktf_provider_aws/py.typed
github_actions_cdk/cdktf_provider_aws/_jsii/__init__.py
github_actions_cdk/cdktf_provider_aws/_jsii/cdktf-provider-aws@0.0.23.jsii.tgz
github_actions_cdk.cdktf_provider_aws-0.0.23.dist-info/LICENSE
github_actions_cdk.cdktf_provider_aws-0.0.23.dist-info/METADATA
github_actions_cdk.cdktf_provider_aws-0.0.23.dist-info/WHEEL
github_actions_cdk.cdktf_provider_aws-0.0.23.dist-info/top_level.txt
github_actions_cdk.cdktf_provider_aws-0.0.23.dist-info/RECORD
